lob_random/__init__.py
lob_random/lob.py
lob_random-1.0.0.dist-info/METADATA
lob_random-1.0.0.dist-info/WHEEL
lob_random-1.0.0.dist-info/entry_points.txt
lob_random-1.0.0.dist-info/top_level.txt
lob_random-1.0.0.dist-info/RECORD
