Metadata-Version: 2.4
Name: lob-random
Version: 1.0.0
Classifier: Programming Language :: Python :: 3
Classifier: License :: OSI Approved :: MIT License
Classifier: Operating System :: OS Independent
Requires-Dist: requests
Requires-Dist: lxml
Requires-Dist: beautifulsoup4
Dynamic: classifier
Dynamic: requires-dist
